ComputationalAndInferentialThinkingUcbData8/README.md
ComputationalAndInferentialThinkingUcbData8/__init__.py
ComputationalAndInferentialThinkingUcbData8/__main__.py
ComputationalAndInferentialThinkingUcbData8/file.epub
ComputationalAndInferentialThinkingUcbData8/index.html
ComputationalAndInferentialThinkingUcbData8/css/__init__.py
ComputationalAndInferentialThinkingUcbData8/css/annotations.css
ComputationalAndInferentialThinkingUcbData8/css/main.css
ComputationalAndInferentialThinkingUcbData8/css/normalize.css
ComputationalAndInferentialThinkingUcbData8/css/popup.css
ComputationalAndInferentialThinkingUcbData8/font/__init__.py
ComputationalAndInferentialThinkingUcbData8/font/fontello.eot
ComputationalAndInferentialThinkingUcbData8/font/fontello.svg
ComputationalAndInferentialThinkingUcbData8/font/fontello.ttf
ComputationalAndInferentialThinkingUcbData8/font/fontello.woff
ComputationalAndInferentialThinkingUcbData8/img/__init__.py
ComputationalAndInferentialThinkingUcbData8/img/annotator-glyph-sprite.png
ComputationalAndInferentialThinkingUcbData8/img/annotator-icon-sprite.png
ComputationalAndInferentialThinkingUcbData8/img/apple-touch-icon.png
ComputationalAndInferentialThinkingUcbData8/img/cancelfullscreen.png
ComputationalAndInferentialThinkingUcbData8/img/close.png
ComputationalAndInferentialThinkingUcbData8/img/fullscreen.png
ComputationalAndInferentialThinkingUcbData8/img/loader.gif
ComputationalAndInferentialThinkingUcbData8/img/menu-icon.png
ComputationalAndInferentialThinkingUcbData8/img/save.png
ComputationalAndInferentialThinkingUcbData8/img/saved.png
ComputationalAndInferentialThinkingUcbData8/img/settings-s.png
ComputationalAndInferentialThinkingUcbData8/img/settings.png
ComputationalAndInferentialThinkingUcbData8/img/star.png
ComputationalAndInferentialThinkingUcbData8/js/__init__.py
ComputationalAndInferentialThinkingUcbData8/js/epub.js
ComputationalAndInferentialThinkingUcbData8/js/epub.min.js
computational_and_inferential_thinking_ucb_data8-2024.3.2.0.dist-info/METADATA
computational_and_inferential_thinking_ucb_data8-2024.3.2.0.dist-info/WHEEL
computational_and_inferential_thinking_ucb_data8-2024.3.2.0.dist-info/entry_points.txt
computational_and_inferential_thinking_ucb_data8-2024.3.2.0.dist-info/top_level.txt
computational_and_inferential_thinking_ucb_data8-2024.3.2.0.dist-info/RECORD
